emulator/__init__.py
emulator/api/__init__.py
emulator/api/emulator_server.py
emulator/cli/__init__.py
emulator/cli/cmd_cli.py
emulator/cli/main.py
emulator/commands/__init__.py
emulator/commands/dispatcher.py
emulator/commands/sacct.py
emulator/commands/sacctmgr.py
emulator/core/__init__.py
emulator/core/database.py
emulator/core/slurm_config.py
emulator/core/time_engine.py
emulator/core/usage_simulator.py
emulator/periodic_limits/__init__.py
emulator/periodic_limits/calculator.py
emulator/periodic_limits/qos_manager.py
emulator/scenarios/__init__.py
emulator/scenarios/limits_configuration_scenarios.py
emulator/scenarios/scenario_registry.py
emulator/scenarios/sequence_scenario.py
slurm_emulator-0.1.1.dist-info/METADATA
slurm_emulator-0.1.1.dist-info/WHEEL
slurm_emulator-0.1.1.dist-info/entry_points.txt
slurm_emulator-0.1.1.dist-info/licenses/LICENSE
slurm_emulator-0.1.1.dist-info/RECORD
