Metadata-Version: 2.4
Name: slurm-emulator
Version: 0.1.1
Summary: SLURM command emulator with time manipulation for testing periodic limits
Project-URL: Homepage, https://waldur.com
Project-URL: Documentation, https://docs.waldur.com
Project-URL: Repository, https://gitlab.com/waldur/slurm-emulator
Author-email: Waldur Team <info@waldur.com>
License-Expression: MIT
License-File: LICENSE
Classifier: Development Status :: 4 - Beta
Classifier: Intended Audience :: Developers
Classifier: License :: OSI Approved :: MIT License
Classifier: Operating System :: OS Independent
Classifier: Programming Language :: Python :: 3
Classifier: Programming Language :: Python :: 3.9
Classifier: Programming Language :: Python :: 3.10
Classifier: Programming Language :: Python :: 3.11
Classifier: Programming Language :: Python :: 3.12
Classifier: Programming Language :: Python :: 3.13
Classifier: Topic :: Software Development :: Testing
Classifier: Topic :: System :: Systems Administration
Requires-Python: >=3.9
Requires-Dist: click>=8.0.0
Requires-Dist: fastapi>=0.100.0
Requires-Dist: pydantic>=2.0.0
Requires-Dist: python-dateutil>=2.8.0
Requires-Dist: pyyaml>=6.0
Requires-Dist: uvicorn>=0.20.0
Provides-Extra: dev
Requires-Dist: black>=23.0.0; extra == 'dev'
Requires-Dist: mypy>=1.0.0; extra == 'dev'
Requires-Dist: pre-commit>=3.0.0; extra == 'dev'
Requires-Dist: pytest-cov>=4.0.0; extra == 'dev'
Requires-Dist: pytest>=7.0.0; extra == 'dev'
Requires-Dist: ruff>=0.12.1; extra == 'dev'
Requires-Dist: types-python-dateutil; extra == 'dev'
Requires-Dist: types-pyyaml; extra == 'dev'
Requires-Dist: types-requests; extra == 'dev'
